bragerone/__init__.py
bragerone/__main__.py
bragerone/api.py
bragerone/const.py
bragerone/gateway.py
bragerone/labels.py
bragerone/ws.py
py_bragerone-0.2.4.dist-info/licenses/LICENSE
py_bragerone-0.2.4.dist-info/METADATA
py_bragerone-0.2.4.dist-info/WHEEL
py_bragerone-0.2.4.dist-info/entry_points.txt
py_bragerone-0.2.4.dist-info/top_level.txt
py_bragerone-0.2.4.dist-info/RECORD
