Metadata-Version: 2.4
Name: py-bragerone
Version: 0.2.4
Summary: Brager One client: REST + WebSocket + label resolver for Home Assistant & tools
Author: ChatGPT5
Author-email: MarPi82 <marpi82@users.noreply.github.com>
Maintainer-email: MarPi82 <marpi82@users.noreply.github.com>
License: MIT License
Project-URL: Homepage, https://github.com/marpi82/py-bragerone
Project-URL: Issues, https://github.com/marpi82/py-bragerone/issues
Classifier: License :: OSI Approved :: MIT License
Classifier: Programming Language :: Python :: 3
Classifier: Programming Language :: Python :: 3.10
Classifier: Programming Language :: Python :: 3.11
Classifier: Programming Language :: Python :: 3.12
Classifier: Operating System :: OS Independent
Classifier: Topic :: Home Automation
Requires-Python: >=3.10
License-File: LICENSE
Requires-Dist: aiohttp>=3.9
Requires-Dist: python-socketio[asyncio_client]>=5.11
Provides-Extra: test
Requires-Dist: pytest>=8; extra == "test"
Requires-Dist: pytest-asyncio>=0.23; extra == "test"
Requires-Dist: packaging>=24; extra == "test"
Dynamic: license-file
